neuralee/__init__.py
neuralee/embedding.py
neuralee/_aux/__init__.py
neuralee/_aux/affinity.py
neuralee/_aux/embeddingsLoss.py
neuralee/_aux/error.py
neuralee/_aux/gradient.py
neuralee/_aux/linearsearch.py
neuralee/_aux/visualize.py
neuralee/dataset/__init__.py
neuralee/dataset/anndata.py
neuralee/dataset/brain_large.py
neuralee/dataset/cite_seq.py
neuralee/dataset/cortex.py
neuralee/dataset/csv.py
neuralee/dataset/dataset.py
neuralee/dataset/dataset10X.py
neuralee/dataset/hemato.py
neuralee/dataset/loom.py
neuralee/dataset/pbmc.py
neuralee/dataset/seqfish.py
neuralee/dataset/smfish.py
neuralee-0.1.6.dist-info/LICENSE
neuralee-0.1.6.dist-info/METADATA
neuralee-0.1.6.dist-info/WHEEL
neuralee-0.1.6.dist-info/top_level.txt
neuralee-0.1.6.dist-info/RECORD
