Metadata-Version: 2.1
Name: neuralee
Version: 0.1.6
Summary: NeuralEE: a GPU-accelerated elastic embedding dimensionality reduction method for visualization of large-scale scRNA-seq data
Home-page: https://github.com/HibearME/NeuralEE
Author: Jiankang Xiong
Author-email: hibearme@163.com
License: MIT license
Keywords: neuralee
Platform: UNKNOWN
Classifier: Development Status :: 4 - Beta
Classifier: Intended Audience :: Science/Research
Classifier: License :: OSI Approved :: MIT License
Classifier: Programming Language :: Python :: 3.7
Classifier: Operating System :: MacOS :: MacOS X
Classifier: Operating System :: Microsoft :: Windows
Classifier: Operating System :: POSIX :: Linux
Classifier: Topic :: Scientific/Engineering :: Bio-Informatics
Requires-Dist: numpy (>=1.16.3)
Requires-Dist: scipy (>=1.1.0)
Requires-Dist: torch (>=1.0.1)
Requires-Dist: matplotlib (>=2.2.3)
Requires-Dist: tqdm (>=4.26.0)
Requires-Dist: anndata (>=0.6.19)
Requires-Dist: scikit-learn (>=0.19.2)
Requires-Dist: h5py (>=2.8.0)
Requires-Dist: pandas (>=0.23.4)
Requires-Dist: loompy (>=2.0.17)
Requires-Dist: jupyter (>=1.0.0)
Requires-Dist: ipython (>=6.5.0)
